LICENSE.md
README.md
pyproject.toml
aviary_models/__init__.py
aviary_models/py.typed
aviary_models/sursentia/__init__.py
aviary_models/sursentia/model.py
aviary_models/sursentia/sliding_window_inference.py
aviary_models/sursentia/sursentia.py
geospaitial_lab_aviary_models.egg-info/PKG-INFO
geospaitial_lab_aviary_models.egg-info/SOURCES.txt
geospaitial_lab_aviary_models.egg-info/dependency_links.txt
geospaitial_lab_aviary_models.egg-info/entry_points.txt
geospaitial_lab_aviary_models.egg-info/requires.txt
geospaitial_lab_aviary_models.egg-info/top_level.txt