Metadata-Version: 2.4
Name: geospaitial-lab-aviary-models
Version: 0.1.2
Summary: Models for aviary
Author-email: Marius Maryniak <marius.maryniak@w-hs.de>, Alexander Roß <alexander.ross@w-hs.de>
Maintainer-email: Marius Maryniak <marius.maryniak@w-hs.de>, Alexander Roß <alexander.ross@w-hs.de>, Stefan Küpper <stefan.kuepper@w-hs.de>
License: GPL-3.0
Project-URL: Homepage, https://www.github.com/geospaitial-lab/aviary-models
Project-URL: Documentation, https://geospaitial-lab.github.io/aviary
Classifier: License :: OSI Approved :: GNU General Public License v3 (GPLv3)
Classifier: Operating System :: OS Independent
Classifier: Programming Language :: Python
Classifier: Programming Language :: Python :: 3
Classifier: Programming Language :: Python :: 3.10
Classifier: Programming Language :: Python :: 3.11
Classifier: Programming Language :: Python :: 3.12
Classifier: Topic :: Scientific/Engineering :: Artificial Intelligence
Classifier: Topic :: Scientific/Engineering :: GIS
Requires-Python: >=3.10
License-File: LICENSE.md
Requires-Dist: geospaitial-lab-aviary>=1.0.0b4
Provides-Extra: sursentia
Requires-Dist: huggingface_hub>=1.1.0; extra == "sursentia"
Provides-Extra: all
Requires-Dist: huggingface_hub>=1.1.0; extra == "all"
Dynamic: license-file
